[
  {
    "answers": [
      {
        "id": 375741,
        "content_html": "<span data-math=\"1.93 \\times 10^4\\,\\text{N/m}\">1.93 \\times 10^4\\,\\text{N/m}</span>",
        "correctness": "1.0",
        "feedback_html": "Using Hooke’s Law, the value of the force constant comes out to be <span data-math=\"1.93 \\times 10^4\\,\\text{N/m}\">1.93 \\times 10^4\\,\\text{N/m}</span>."
      },
      {
        "id": 375738,
        "content_html": "<span data-math=\"1.97 \\times 10^3\\,\\text{N/m}\">1.97 \\times 10^3\\,\\text{N/m}</span>",
        "correctness": "0.0",
        "feedback_html": "The force will be the weight of the <span data-math=\"65\\,\\text{kg}\">65\\,\\text{kg}</span> person sitting inside the car. Try to find weight when mass is given."
      },
      {
        "id": 375739,
        "content_html": "<span data-math=\"1.93 \\times 10^2\\,\\text{N/m}\">1.93 \\times 10^2\\,\\text{N/m}</span>",
        "correctness": "0.0",
        "feedback_html": "Be careful about the units. Keep all quantities in SI units, to obtain the force constant in <span data-math=\"\\text{N/m}\">\\text{N/m}</span>."
      },
      {
        "id": 375740,
        "content_html": "<span data-math=\"1.97 \\times 10^1\\,\\text{N/m}\">1.97 \\times 10^1\\,\\text{N/m}</span>",
        "correctness": "0.0",
        "feedback_html": "The force is mass times acceleration due to gravity. Also, convert the displacement of the suspension system given in centimeters to meters, so that the unit for the force constant is <span data-math=\"\\text{N/m}\">\\text{N/m}</span>."
      }
    ],
    "group_uuid": "b80b96ed-3889-447f-a9df-d3a530d767eb",
    "stem_html": "What is the force constant for the suspension system of a car that settles <span data-math=\"3.3\\,\\text{cm}\">3.3\\,\\text{cm}</span> when a <span data-math=\"65\\,\\text{kg}\">65\\,\\text{kg}</span> person gets in?",
    "tags": "b80b96ed-3889-447f-a9df-d3a530d767eb",
    "uid": "2289@5"
  },
  {
    "answers": [
      {
        "id": 375752,
        "content_html": "The negative sign indicates that displacement decreases with increasing force.",
        "correctness": "0.0",
        "feedback_html": "Review Hooke’s law. Force is directly proportional to the displacement."
      },
      {
        "id": 375751,
        "content_html": "The negative sign indicates that the direction of the applied force is opposite to that of displacement.",
        "correctness": "0.0",
        "feedback_html": "Hooke’s law gives the equation <span data-math=\"F = {-k}x\">F = {-k}x</span>. Here, <span data-math=\"F\">F</span> is the restoring force, not the applied force."
      },
      {
        "id": 375753,
        "content_html": "The negative sign indicates that the direction of the restoring force is opposite to that of displacement.",
        "correctness": "1.0",
        "feedback_html": "The negative sign indicates that <span data-math=\"F\">F</span> and <span data-math=\"x\">x</span> must have opposite signs."
      },
      {
        "id": 375750,
        "content_html": "The negative sign indicates that the force constant must be negative.",
        "correctness": "0.0",
        "feedback_html": "Force constant is always a positive quantity."
      }
    ],
    "group_uuid": "f4d4b751-f6a6-4af6-a7aa-435332272403",
    "stem_html": "Why is there a negative sign in the equation for Hooke’s law?",
    "tags": "f4d4b751-f6a6-4af6-a7aa-435332272403",
    "uid": "2295@6"
  },
  {
    "answers": [
      {
        "id": 375773,
        "content_html": "<span data-math=\"15^\\circ\">15^\\circ</span>",
        "correctness": "1.0",
        "feedback_html": "For larger angles, the motion is no longer governed by Hooke’s law."
      },
      {
        "id": 375772,
        "content_html": "<span data-math=\"45^\\circ\">45^\\circ</span>",
        "correctness": "0.0",
        "feedback_html": "<span data-math=\"45^\\circ\\!\">45^\\circ\\!</span> is one fourth of <span data-math=\"180^\\circ\\!\">180^\\circ\\!</span>. With this amplitude, the motion is not simple harmonic."
      },
      {
        "id": 375771,
        "content_html": "<span data-math=\"75^\\circ\">75^\\circ</span>",
        "correctness": "0.0",
        "feedback_html": "Think about how large this amplitude is; the motion of a simple pendulum is no longer a simple harmonic."
      },
      {
        "id": 375770,
        "content_html": "<span data-math=\"90^\\circ\">90^\\circ</span>",
        "correctness": "0.0",
        "feedback_html": "This amplitude is very large and the resulting motion won’t be simple harmonic in nature."
      }
    ],
    "group_uuid": "b5a71574-96c0-42b6-be27-0fedce1e89d4",
    "stem_html": "Up to approximately what angle is simple harmonic motion a good model for a pendulum?",
    "tags": "b5a71574-96c0-42b6-be27-0fedce1e89d4",
    "uid": "2303@7"
  },
  {
    "answers": [
      {
        "id": 346868,
        "content_html": "No, it is not a natural science because it is not used in the study of the natural world.",
        "correctness": "0.0",
        "feedback_html": "Mathematics is used in the study of the natural world, but that does not explain whether it is a natural science."
      },
      {
        "id": 346871,
        "content_html": "No, it is not a natural science. Mathematics focuses on understanding mathematical relations and calculations, which is useful in natural sciences but which is distinct.",
        "correctness": "1.0",
        "feedback_html": "Mathematics is not a natural science as it does not use chemical and physical measurements like other fields in natural sciences."
      },
      {
        "id": 346869,
        "content_html": "Yes, it is a natural science. Mathematics deals with verifying the experimental data.",
        "correctness": "0.0",
        "feedback_html": "Mathematics does not use the chemical and physical measurements, therefore it is not natural science."
      },
      {
        "id": 346870,
        "content_html": "Yes, it is a natural science. It uses chemical and physical measurements.",
        "correctness": "0.0",
        "feedback_html": "Mathematics does not use chemical and physical measurements."
      }
    ],
    "group_uuid": "e8f5e09d-8f5d-4ec2-ac56-72688133a2e7",
    "stem_html": "Is mathematics a natural science? Explain your reasoning.",
    "tags": "e8f5e09d-8f5d-4ec2-ac56-72688133a2e7",
    "uid": "7@6"
  }
]